Metadata-Version: 1.0
Name: meo-distributions
Version: 0.1
Summary: Gaussian distribution and Binomial Distribution
Home-page: UNKNOWN
Author: Moses Egbo
Author-email: UNKNOWN
License: UNKNOWN
Platform: UNKNOWN
